CHANGELOG.rst
LICENSE.txt
MANIFEST.in
README.rst
owncloud_backup.py
requirements.txt
setup.py
owncloud_backup.egg-info/PKG-INFO
owncloud_backup.egg-info/SOURCES.txt
owncloud_backup.egg-info/dependency_links.txt
owncloud_backup.egg-info/requires.txt
owncloud_backup.egg-info/top_level.txt
owncloud_backup.egg-info/zip-safe
tests/test_backup.py
tests/.cache/v/cache/lastfailed