Metadata-Version: 1.1
Name: owncloud-backup
Version: 0.1.2
Summary: backupper for uploading and managing files in ownCloud.
Home-page: https://github.com/NLCR/owncloud_backup
Author: Bystroushaak
Author-email: bystrousak[at]kitakitsune.org
License: MIT
Platform: UNKNOWN
Classifier: Development Status :: 3 - Alpha
Classifier: Programming Language :: Python
Classifier: Programming Language :: Python :: 2.7
Classifier: Intended Audience :: Developers
Classifier: License :: OSI Approved :: MIT License
